{
  "file": "zh-page-338-img-1.png",
  "source_page": 338,
  "width": 1679,
  "height": 391,
  "file_size": 158454,
  "description": "An illustrative figure. OCR preview: \"=E Be x ie  ia RON KAR  > fill EI EB nHERR “SMA, BMA °° Eom MERA IME - HIER MA BL ale  ° Xl  ° AAA BA\"",
  "ocr_text": "=E Be x ie\n\nia RON KAR\n\n> fill EI EB nHERR “SMA, BMA °° Eom MERA IME\n- HIER MA BL ale\n\n° Xl\n\n° AAA BA\n\n",
  "category": "decorative",
  "keywords": [
    "ron",
    "kar",
    "fill",
    "nherr",
    "sma"
  ]
}